{
  "timestamp": 1743019767.602135,
  "expiry": 86400,
  "results": [
    {
      "title": "[No results found in Semantic Scholar]",
      "authors": [],
      "abstract": "The term '(title:katabatic)^2.0 OR (abstract:katabatic)^3.0 OR (author:katabatic)^13.5 OR (year:katabatic)^0.5 OR (title:wind)^2.0 OR (abstract:wind)^3.0 OR (author:wind)^13.5 OR (year:wind)^0.5 OR (title:\"katabatic wind\")^2.0 OR (abstract:\"katabatic wind\")^3.0 OR (author:\"katabatic wind\")^13.5 OR (year:\"katabatic wind\")^0.5' did not match any documents in Semantic Scholar, or the API rate limit was exceeded.",
      "doi": null,
      "year": null,
      "url": "https://www.semanticscholar.org/",
      "source": "semanticScholar",
      "rank": 1,
      "citation_count": 0,
      "doctype": null,
      "property": null,
      "original_rank": null,
      "rank_change": null,
      "original_score": null,
      "boosted_score": null,
      "boost_factors": null
    }
  ]
}